zensols/amrspring/__init__.py
zensols/amrspring/app.py
zensols/amrspring/cli.py
zensols/amrspring/resources/app.conf
zensols/amrspring/resources/default.conf
zensols/amrspring/resources/obj.yml
zensols.amrspring-0.0.1.dist-info/METADATA
zensols.amrspring-0.0.1.dist-info/WHEEL
zensols.amrspring-0.0.1.dist-info/entry_points.txt
zensols.amrspring-0.0.1.dist-info/top_level.txt
zensols.amrspring-0.0.1.dist-info/RECORD
