Metadata-Version: 2.1
Name: zensols.amrspring
Version: 0.0.1
Summary: A client and server that generates AMR graphs from natural language sentences.
Home-page: https://github.com/plandes/amrspring
Download-URL: https://github.com/plandes/amrspring/releases/download/v0.0.1/zensols.amrspring-0.0.1-py3-none-any.whl
Author: Paul Landes
Author-email: landes@mailc.net
Keywords: tooling
Requires-Dist: zensols.util ~=1.14.0
